opvault/__init__.py
opvault/category.py
opvault/cli.py
opvault/designation_types.py
opvault/exceptions.py
opvault/field_types.py
opvault/onepass.py
opvault-0.4.9.dist-info/LICENSE
opvault-0.4.9.dist-info/METADATA
opvault-0.4.9.dist-info/WHEEL
opvault-0.4.9.dist-info/entry_points.txt
opvault-0.4.9.dist-info/top_level.txt
opvault-0.4.9.dist-info/RECORD
